bdkpython/__init__.py
bdkpython/bdk.py
bdkpython/bdkffi.dll
bdkpython-2.2.0.dist-info/licenses/LICENSE-APACHE
bdkpython-2.2.0.dist-info/licenses/LICENSE-MIT
bdkpython-2.2.0.dist-info/METADATA
bdkpython-2.2.0.dist-info/WHEEL
bdkpython-2.2.0.dist-info/top_level.txt
bdkpython-2.2.0.dist-info/RECORD
