Metadata-Version: 2.4
Name: bdkpython
Version: 2.2.0
Summary: The Python language bindings for the Bitcoin Development Kit
Author-email: Bitcoin Dev Kit Developers <dev@bitcoindevkit.org>
License-Expression: MIT OR Apache-2.0
Project-URL: Homepage, https://github.com/bitcoindevkit
Project-URL: Repository, https://github.com/bitcoindevkit/bdk-python
Keywords: bitcoin,bdk,wallet,ffi,rust
Classifier: Programming Language :: Python :: 3
Classifier: Operating System :: OS Independent
Requires-Python: >=3.10
License-File: LICENSE-MIT
License-File: LICENSE-APACHE
Dynamic: license-file
